{
  "descriptionHash": "175FEC08E0017703402BC19CCEF53A7F253A470F760C7CB17ED872603E3D162B2363F586A3032FB93D6AB93B11365E46136EC72A8C54782477E0A3F5960E60C4",
  "descriptionLocation": "../../fixed.json",
  "lockFileVersion": "1.0.0",
  "kiotaVersion": "1.31.1",
  "clientClassName": "ElevenLabsOpenApiClient",
  "typeAccessModifier": "Public",
  "clientNamespaceName": "Soenneker.ElevenLabs.OpenApiClient",
  "language": "CSharp",
  "usesBackingStore": false,
  "excludeBackwardCompatible": true,
  "includeAdditionalData": true,
  "disableSSLValidation": false,
  "serializers": [
    "Microsoft.Kiota.Serialization.Json.JsonSerializationWriterFactory",
    "Microsoft.Kiota.Serialization.Text.TextSerializationWriterFactory",
    "Microsoft.Kiota.Serialization.Form.FormSerializationWriterFactory",
    "Microsoft.Kiota.Serialization.Multipart.MultipartSerializationWriterFactory"
  ],
  "deserializers": [
    "Microsoft.Kiota.Serialization.Json.JsonParseNodeFactory",
    "Microsoft.Kiota.Serialization.Text.TextParseNodeFactory",
    "Microsoft.Kiota.Serialization.Form.FormParseNodeFactory"
  ],
  "structuredMimeTypes": [
    "application/json",
    "text/plain;q=0.9",
    "application/x-www-form-urlencoded;q=0.2",
    "multipart/form-data;q=0.1"
  ],
  "includePatterns": [],
  "excludePatterns": [],
  "disabledValidationRules": []
}