{
  "descriptionHash": "5E34246299C7778FFF46D314BE8956C6ED45216C9793744BF9E850AD25F1CD939CCA3E3A2F0F0334591E2AAFAA2BFC1D65ED5B24560088D6E4CFB1E73032D48E",
  "descriptionLocation": "../../fixed.json",
  "lockFileVersion": "1.0.0",
  "kiotaVersion": "1.34.1",
  "clientClassName": "ElevenLabsOpenApiClient",
  "typeAccessModifier": "Public",
  "clientNamespaceName": "Soenneker.ElevenLabs.OpenApiClient",
  "language": "CSharp",
  "usesBackingStore": false,
  "excludeBackwardCompatible": true,
  "includeAdditionalData": true,
  "disableSSLValidation": false,
  "serializers": [
    "Microsoft.Kiota.Serialization.Json.JsonSerializationWriterFactory",
    "Microsoft.Kiota.Serialization.Text.TextSerializationWriterFactory",
    "Microsoft.Kiota.Serialization.Form.FormSerializationWriterFactory",
    "Microsoft.Kiota.Serialization.Multipart.MultipartSerializationWriterFactory"
  ],
  "deserializers": [
    "Microsoft.Kiota.Serialization.Json.JsonParseNodeFactory",
    "Microsoft.Kiota.Serialization.Text.TextParseNodeFactory",
    "Microsoft.Kiota.Serialization.Form.FormParseNodeFactory"
  ],
  "structuredMimeTypes": [
    "application/json",
    "text/plain;q=0.9",
    "application/x-www-form-urlencoded;q=0.2",
    "multipart/form-data;q=0.1"
  ],
  "includePatterns": [],
  "excludePatterns": [],
  "disabledValidationRules": [],
  "allowedExternalOrigins": []
}